tessellation/__init__.py
tessellation/draw.py
tessellation/procgen/__init__.py
tessellation/procgen/action.py
tessellation/procgen/ga/__init__.py
tessellation/procgen/ga/ga_generator.py
tessellation/procgen/ga/genome.py
tessellation/procgen/ga/heuristic.py
tessellation/procgen/ga/mutate.py
tessellation/procgen/ga/problem.py
tessellation/procgen/generation_result.py
tessellation/procgen/generator.py
tessellation/procgen/rng/__init__.py
tessellation/procgen/rng/rng_generator.py
tessellation/procgen/tessellation_type.py
tessellation-0.1.0.dist-info/LICENSE
tessellation-0.1.0.dist-info/WHEEL
tessellation-0.1.0.dist-info/METADATA
tessellation-0.1.0.dist-info/RECORD
